epub_metadata/__init__.py
epub_metadata/book.py
epub_metadata/epub.py
epub_metadata/file.py
epub_editor-0.0.3.dist-info/LICENSE
epub_editor-0.0.3.dist-info/METADATA
epub_editor-0.0.3.dist-info/WHEEL
epub_editor-0.0.3.dist-info/entry_points.txt
epub_editor-0.0.3.dist-info/top_level.txt
epub_editor-0.0.3.dist-info/RECORD
